{
  "version": "5.2.1",
  "flags": {},
  "shapes": [
    {
      "label": "cat_4",
      "points": [
        [
          126.79083094555874,
          4.5386819484240775
        ],
        [
          485.53008595988535,
          281.32951289398284
        ]
      ],
      "group_id": null,
      "description": "",
      "shape_type": "rectangle",
      "flags": {}
    }
  ],
  "imagePath": "..\\cat_12_train_result\\cat_4_75.jpg",
  "imageData": null,
  "imageHeight": 332,
  "imageWidth": 500
}